torchlm/__init__.py
torchlm/command.py
torchlm/version.py
torchlm/core/__init__.py
torchlm/core/core.py
torchlm/data/__init__.py
torchlm/data/_annotools.py
torchlm/data/_converters.py
torchlm/data/data.py
torchlm/metrics/__init__.py
torchlm/metrics/metrics.py
torchlm/models/__init__.py
torchlm/models/_base.py
torchlm/models/_utils.py
torchlm/models/models.py
torchlm/models/anchorface/__init__.py
torchlm/models/nanopoint/__init__.py
torchlm/models/pfld/__init__.py
torchlm/models/pipnet/__init__.py
torchlm/models/pipnet/_cfgs.py
torchlm/models/pipnet/_data.py
torchlm/models/pipnet/_impls.py
torchlm/models/pipnet/_utils.py
torchlm/models/pipnet/pipnet.py
torchlm/models/yolov5/__init__.py
torchlm/models/yolox/__init__.py
torchlm/runtime/__init__.py
torchlm/runtime/_runtime.py
torchlm/runtime/_wrappers.py
torchlm/runtime/runtime.py
torchlm/runtime/ort/__init__.py
torchlm/runtime/ort/_faceboxesv2.py
torchlm/runtime/ort/_pfld.py
torchlm/runtime/ort/_pipnet.py
torchlm/runtime/ort/_scrfd.py
torchlm/runtime/ort/_yolov5face.py
torchlm/runtime/ort/assets/faceboxesv2-640x640.onnx
torchlm/runtime/ort/assets/yolov5face-n-0.5-640x640.onnx
torchlm/runtime/trt/__init__.py
torchlm/smooth/__init__.py
torchlm/smooth/smooth.py
torchlm/tools/__init__.py
torchlm/tools/_align.py
torchlm/tools/_faceboxesv2.py
torchlm/tools/tools.py
torchlm/tools/assets/faceboxesv2.pth
torchlm/trackers/__init__.py
torchlm/trackers/trackers.py
torchlm/transforms/__init__.py
torchlm/transforms/_autodtypes.py
torchlm/transforms/_functional.py
torchlm/transforms/transforms.py
torchlm/transforms/assets/1.jpg
torchlm/transforms/assets/10.jpg
torchlm/transforms/assets/100.jpg
torchlm/transforms/assets/101.jpg
torchlm/transforms/assets/102.jpg
torchlm/transforms/assets/103.jpg
torchlm/transforms/assets/104.jpg
torchlm/transforms/assets/105.jpg
torchlm/transforms/assets/108.jpg
torchlm/transforms/assets/109.jpg
torchlm/transforms/assets/11.jpg
torchlm/transforms/assets/110.jpg
torchlm/transforms/assets/111.jpg
torchlm-0.1.6.10.dist-info/LICENSE
torchlm-0.1.6.10.dist-info/METADATA
torchlm-0.1.6.10.dist-info/WHEEL
torchlm-0.1.6.10.dist-info/top_level.txt
torchlm-0.1.6.10.dist-info/RECORD
