Metadata-Version: 2.1
Name: torchlm
Version: 0.1.6.10
Summary: A PyTorch landmarks-only library with 100+ data augmentations, training and inference, can easily install with pip and compatible with albumentations and torchvision.
Home-page: https://github.com/DefTruth/torchlm
Author: DefTruth
Author-email: qyjdef@163.com
License: UNKNOWN
Platform: UNKNOWN
Classifier: Programming Language :: Python :: 3
Classifier: Programming Language :: Python :: 3.6
Classifier: Programming Language :: Python :: 3.7
Classifier: Programming Language :: Python :: 3.8
Classifier: Programming Language :: Python :: 3.9
Classifier: License :: OSI Approved :: MIT License
Classifier: Operating System :: OS Independent
Requires-Dist: opencv-python (>=4.3.0)
Requires-Dist: numpy (>=1.14.4)
Requires-Dist: torch (>=1.6.0)
Requires-Dist: torchvision (>=0.8.0)
Requires-Dist: onnx (>=1.8.0)
Requires-Dist: onnxruntime (>=1.7.0)
Requires-Dist: tqdm (>=4.10.0)
Requires-Dist: hdf5storage (>=0.1.18)
Requires-Dist: pandas (>=1.2.1)
Requires-Dist: scipy (>=1.6.2)
